vector_swizzling/__init__.py
vector_swizzling-0.2.0.dist-info/METADATA
vector_swizzling-0.2.0.dist-info/WHEEL
vector_swizzling-0.2.0.dist-info/top_level.txt
vector_swizzling-0.2.0.dist-info/RECORD
