Metadata-Version: 2.4
Name: vector-swizzling
Version: 0.2.0
Summary: A versatile vector operations module to use with numpy to add swizzling capabilities for 2D, 3D, and 4D vectors.
Home-page: https://github.com/ikz87/python-vector-swizzling
Author: Isaac Arcia
Author-email: i.arcia135@gmail.com
Classifier: Programming Language :: Python :: 3
Classifier: License :: OSI Approved :: MIT License
Classifier: Operating System :: OS Independent
Requires-Python: >=3.6
Requires-Dist: numpy
Dynamic: author
Dynamic: author-email
Dynamic: classifier
Dynamic: description
Dynamic: description-content-type
Dynamic: home-page
Dynamic: requires-dist
Dynamic: requires-python
Dynamic: summary
